flotorch/__init__.py
flotorch/adk/__init__.py
flotorch/adk/agent.py
flotorch/adk/llm.py
flotorch/adk/memory.py
flotorch/adk/sessions.py
flotorch/adk/utils/__init__.py
flotorch/adk/utils/adk_utils.py
flotorch/adk/utils/warning_utils.py
flotorch/autogen/__init__.py
flotorch/autogen/agent.py
flotorch/autogen/llm.py
flotorch/autogen/memory.py
flotorch/autogen/sessions.py
flotorch/autogen/utils/autogen_utils.py
flotorch/crewai/__init__.py
flotorch/crewai/agent.py
flotorch/crewai/llm.py
flotorch/crewai/memory.py
flotorch/crewai/sessions.py
flotorch/langchain/agent.py
flotorch/langchain/llm.py
flotorch/langchain/memory.py
flotorch/langchain/session.py
flotorch/langchain/utils/llm_utils.py
flotorch/langgraph/__init__.py
flotorch/langgraph/agent.py
flotorch/langgraph/memory.py
flotorch/langgraph/sessions.py
flotorch/sdk/__init__.py
flotorch/sdk/llm.py
flotorch/sdk/memory.py
flotorch/sdk/session.py
flotorch/sdk/utils/__init__.py
flotorch/sdk/utils/http_utils.py
flotorch/sdk/utils/llm_utils.py
flotorch/sdk/utils/logging_utils.py
flotorch/sdk/utils/memory_utils.py
flotorch/sdk/utils/session_utils.py
flotorch-2.0.0.dist-info/licenses/LICENSE
flotorch-2.0.0.dist-info/METADATA
flotorch-2.0.0.dist-info/WHEEL
flotorch-2.0.0.dist-info/top_level.txt
flotorch-2.0.0.dist-info/RECORD
