Metadata-Version: 2.4
Name: flotorch
Version: 2.0.0
Summary: A modular Python framework for AI agents and LLM interactions
Author-email: Flotorch Team <org.admin@flotorch.ai>
Maintainer-email: Adil Raza <adil.raza@flotorch.ai>, Venkateswarlu Garnimitta <venkateswarlu.garnimitta@flotorch.ai>, Madhu Jangala <madhu.jangala@flotorch.ai>
License: MIT
Project-URL: Homepage, https://github.com/flotorch/flotorch-python
Project-URL: Repository, https://github.com/flotorch/flotorch-python
Project-URL: Documentation, https://docs.flotorch.com
Project-URL: Issues, https://github.com/flotorch/flotorch-python/issues
Classifier: Development Status :: 4 - Beta
Classifier: Intended Audience :: Developers
Classifier: License :: OSI Approved :: MIT License
Classifier: Programming Language :: Python :: 3
Classifier: Programming Language :: Python :: 3.8
Classifier: Programming Language :: Python :: 3.9
Classifier: Programming Language :: Python :: 3.10
Classifier: Programming Language :: Python :: 3.11
Classifier: Programming Language :: Python :: 3.12
Classifier: Topic :: Software Development :: Libraries :: Python Modules
Classifier: Topic :: Scientific/Engineering :: Artificial Intelligence
Classifier: Topic :: Scientific/Engineering :: Information Analysis
Classifier: Framework :: AsyncIO
Classifier: Operating System :: OS Independent
Classifier: Natural Language :: English
Requires-Python: >=3.8
License-File: LICENSE
Requires-Dist: httpx>=0.24
Requires-Dist: pydantic>=1.10
Provides-Extra: sdk
Requires-Dist: httpx>=0.24; extra == "sdk"
Requires-Dist: pydantic>=1.10; extra == "sdk"
Provides-Extra: adk
Requires-Dist: google-adk>=1.5.0; extra == "adk"
Requires-Dist: python-dotenv>=1.0.0; extra == "adk"
Requires-Dist: flotorch[sdk]; extra == "adk"
Provides-Extra: crewai
Requires-Dist: crewai>=0.50.0; extra == "crewai"
Requires-Dist: crewai-tools>=0.60.0; extra == "crewai"
Requires-Dist: crewai-tools[mcp]; extra == "crewai"
Requires-Dist: python-dotenv>=1.0.0; extra == "crewai"
Requires-Dist: flotorch[sdk]; extra == "crewai"
Provides-Extra: autogen
Requires-Dist: python-dotenv>=1.0.0; extra == "autogen"
Requires-Dist: autogen-core>=0.4.0; extra == "autogen"
Requires-Dist: autogen-agentchat>=0.4.0; extra == "autogen"
Requires-Dist: autogen-ext[openai]>=0.4.0; extra == "autogen"
Requires-Dist: openai>=1.0.0; extra == "autogen"
Requires-Dist: mcp>=1.2.0; extra == "autogen"
Requires-Dist: flotorch[sdk]; extra == "autogen"
Provides-Extra: langchain
Requires-Dist: langchain>=0.3.27; extra == "langchain"
Requires-Dist: langchain-openai>=0.2.14; extra == "langchain"
Requires-Dist: langchain-experimental>=0.3.4; extra == "langchain"
Requires-Dist: langchain-community>=0.3.29; extra == "langchain"
Requires-Dist: langgraph>=0.6.6; extra == "langchain"
Requires-Dist: langchain-mcp-tools>=0.2.13; extra == "langchain"
Requires-Dist: langchain-mcp-adapters>=0.1.9; extra == "langchain"
Requires-Dist: langchain-mcp>=0.2.1; extra == "langchain"
Requires-Dist: flotorch[sdk]; extra == "langchain"
Provides-Extra: langgraph
Requires-Dist: langgraph>=0.6.6; extra == "langgraph"
Requires-Dist: langgraph-checkpoint>=2.1.1; extra == "langgraph"
Requires-Dist: langgraph-prebuilt>=0.6.4; extra == "langgraph"
Requires-Dist: langgraph-sdk>=0.2.3; extra == "langgraph"
Requires-Dist: langchain-core>=0.2.14; extra == "langgraph"
Requires-Dist: langchain-community>=0.3.27; extra == "langgraph"
Requires-Dist: langchain-openai>=0.3.30; extra == "langgraph"
Requires-Dist: langchain-mcp-adapters>=0.1.9; extra == "langgraph"
Requires-Dist: mcp>=1.13.1; extra == "langgraph"
Requires-Dist: flotorch[sdk]; extra == "langgraph"
Requires-Dist: flotorch[langchain]; extra == "langgraph"
Provides-Extra: dev
Requires-Dist: build>=0.10.0; extra == "dev"
Requires-Dist: twine>=4.0.0; extra == "dev"
Requires-Dist: pytest>=7.0.0; extra == "dev"
Requires-Dist: pytest-cov>=4.0.0; extra == "dev"
Requires-Dist: black>=23.0.0; extra == "dev"
Requires-Dist: flake8>=6.0.0; extra == "dev"
Requires-Dist: mypy>=1.0.0; extra == "dev"
Dynamic: license-file
